pyh5md/VERSION
pyh5md/__init__.py
pyh5md/h5md_module.py
pyh5md-1.2.0.dist-info/METADATA
pyh5md-1.2.0.dist-info/WHEEL
pyh5md-1.2.0.dist-info/top_level.txt
pyh5md-1.2.0.dist-info/RECORD
