Metadata-Version: 2.4
Name: pyh5md
Version: 1.2.0
Summary: pyh5md - Read and write H5MD files
Author-email: Pierre de Buyl <pdebuyl@pdebuyl.be>
License: BSD-3-Clause
Project-URL: Homepage, https://github.com/pdebuyl/pyh5md
Project-URL: Issues, https://github.com/pdebuyl/pyh5md/issues
Classifier: License :: OSI Approved :: BSD License
Classifier: Programming Language :: Python :: 3
Requires-Python: >=3.9
Requires-Dist: numpy
Requires-Dist: h5py
Provides-Extra: test
Requires-Dist: pytest; extra == "test"
